{
  "total": 194,
  "with_title": 192,
  "without_title": [
    "apple\\DESCRIPTION.md",
    "inference-sh\\DESCRIPTION.md"
  ],
  "parse_errors": [],
  "sample_verified": [
    {
      "file": "agent-browser\\SKILL.md",
      "title": "Agent Browser"
    },
    {
      "file": "algorithmic-art\\SKILL.md",
      "title": "Algorithmic Art"
    },
    {
      "file": "apple\\apple-notes\\SKILL.md",
      "title": "Apple Notes"
    },
    {
      "file": "apple\\apple-reminders\\SKILL.md",
      "title": "Apple Reminders"
    },
    {
      "file": "apple\\findmy\\SKILL.md",
      "title": "Findmy"
    }
  ]
}